dopplersdk/__init__.py
dopplersdk/sdk.py
dopplersdk/setup.py
dopplersdk/hooks/__init__.py
dopplersdk/hooks/hook.py
dopplersdk/models/ActivityLogsList200Response.py
dopplersdk/models/ActivityLogsListResponse.py
dopplersdk/models/ActivityLogsRetrieve200Response.py
dopplersdk/models/AddMemberRequest.py
dopplersdk/models/AddRequest.py
dopplersdk/models/AddResponse.py
dopplersdk/models/AddTrustedIpRequest.py
dopplersdk/models/AddTrustedIpResponse.py
dopplersdk/models/CloneRequest.py
dopplersdk/models/CloneResponse.py
dopplersdk/models/ConfigLogsGet200Response.py
dopplersdk/models/ConfigLogsGetResponse.py
dopplersdk/models/ConfigLogsList200Response.py
dopplersdk/models/ConfigLogsListResponse.py
dopplersdk/models/ConfigLogsRollback200Response.py
dopplersdk/models/ConfigsClone200Response.py
dopplersdk/models/ConfigsCloneRequest.py
dopplersdk/models/ConfigsCreate200Response.py
dopplersdk/models/ConfigsCreateRequest.py
dopplersdk/models/ConfigsCreateResponse.py
dopplersdk/models/ConfigsDelete200Response.py
dopplersdk/models/ConfigsDeleteRequest.py
dopplersdk/models/ConfigsGet200Response.py
dopplersdk/models/ConfigsGetResponse.py
dopplersdk/models/ConfigsList200Response.py
dopplersdk/models/ConfigsListResponse.py
dopplersdk/models/ConfigsLock200Response.py
dopplersdk/models/ConfigsLockRequest.py
dopplersdk/models/ConfigsUnlock200Response.py
dopplersdk/models/ConfigsUnlockRequest.py
dopplersdk/models/ConfigsUpdate200Response.py
dopplersdk/models/ConfigsUpdateRequest.py
dopplersdk/models/ConfigsUpdateResponse.py
dopplersdk/models/CreateRequest.py
dopplersdk/models/CreateResponse.py
dopplersdk/models/DeleteRequest.py
dopplersdk/models/DeleteResponse.py
dopplersdk/models/DeleteTrustedIpRequest.py
dopplersdk/models/DisableResponse.py
dopplersdk/models/DownloadResponse.py
dopplersdk/models/DynamicSecretsIssueLeaseRequest.py
dopplersdk/models/DynamicSecretsRevokeLease200Response.py
dopplersdk/models/DynamicSecretsRevokeLeaseRequest.py
dopplersdk/models/EnableResponse.py
doppler_sdk-1.3.0.dist-info/LICENSE
doppler_sdk-1.3.0.dist-info/METADATA
doppler_sdk-1.3.0.dist-info/WHEEL
doppler_sdk-1.3.0.dist-info/top_level.txt
doppler_sdk-1.3.0.dist-info/RECORD
