Metadata-Version: 2.1
Name: doppler-sdk
Version: 1.3.0
License: MIT
Project-URL: Documentation, https://docs.doppler.com/docs/sdk-python
Project-URL: Source, https://github.com/DopplerHQ/python-sdk
Project-URL: Tracker, https://github.com/DopplerHQ/python-sdk/issues
Project-URL: Homepage, https://doppler.com
Classifier: License :: OSI Approved :: Apache Software License
Classifier: Programming Language :: Python :: 3 :: Only
Classifier: Operating System :: OS Independent
Classifier: Topic :: Security
Requires-Python: >=3.7
License-File: LICENSE
Requires-Dist: requests
Requires-Dist: http-exceptions
Provides-Extra: test
Requires-Dist: pytest ; extra == 'test'
Requires-Dist: responses ; extra == 'test'
